buildflow/__init__.py
buildflow/requests.py
buildflow/responses.py
buildflow/cli/__init__.py
buildflow/cli/file_gen.py
buildflow/cli/main.py
buildflow/cli/utils.py
buildflow/cli/watcher.py
buildflow/config/__init__.py
buildflow/config/_config.py
buildflow/config/buildflow_config.py
buildflow/config/cloud_provider_config.py
buildflow/config/pulumi_config.py
buildflow/core/__init__.py
buildflow/core/utils.py
buildflow/core/app/__init__.py
buildflow/core/app/collector.py
buildflow/core/app/consumer.py
buildflow/core/app/endpoint.py
buildflow/core/app/flow.py
buildflow/core/app/flow_state.py
buildflow/core/app/flow_test.py
buildflow/core/app/service.py
buildflow/core/app/infra/__init__.py
buildflow/core/app/infra/_infra.py
buildflow/core/app/infra/pulumi_workspace.py
buildflow/core/app/infra/actors/__init__.py
buildflow/core/app/infra/actors/infra.py
buildflow/core/app/infra/actors/infra_test.py
buildflow/core/app/runtime/__init__.py
buildflow/core/app/runtime/_runtime.py
buildflow/core/app/runtime/autoscaler.py
buildflow/core/app/runtime/autoscaler_test.py
buildflow/core/app/runtime/fastapi.py
buildflow/core/app/runtime/server.py
buildflow/core/app/runtime/actors/__init__.py
buildflow/core/app/runtime/actors/process_pool.py
buildflow/core/app/runtime/actors/runtime.py
buildflow/core/app/runtime/actors/runtime_test.py
buildflow/core/app/runtime/actors/collector_pattern/__init__.py
buildflow/core/app/runtime/actors/collector_pattern/collector_pool.py
buildflow/core/app/runtime/actors/collector_pattern/receive_process_push_ack.py
buildflow/core/app/runtime/actors/consumer_pattern/__init__.py
buildflow/core/app/runtime/actors/consumer_pattern/consumer_pool.py
buildflow/core/app/runtime/actors/consumer_pattern/consumer_pool_snapshot.py
buildflow/core/app/runtime/actors/consumer_pattern/pull_process_push.py
buildflow/core/app/runtime/actors/consumer_pattern/pull_process_push_test.py
buildflow/core/app/runtime/actors/endpoint_pattern/__init__.py
buildflow-0.3.1.dist-info/LICENSE
buildflow-0.3.1.dist-info/METADATA
buildflow-0.3.1.dist-info/WHEEL
buildflow-0.3.1.dist-info/entry_points.txt
buildflow-0.3.1.dist-info/top_level.txt
buildflow-0.3.1.dist-info/RECORD
