Metadata-Version: 2.1
Name: buildflow
Version: 0.3.1
Summary: BuildFlow, is an open source framework for building large scale systems using Python. All you need to do is describe where your input is coming from and where your output should be written, and BuildFlow handles the rest.
Author-email: Caleb Van Dyke <caleb@launchflow.com>, Josh Tanke <josh@launchflow.com>
Classifier: Development Status :: 2 - Pre-Alpha
Classifier: Intended Audience :: Developers
Classifier: Topic :: Software Development
Classifier: License :: OSI Approved :: Apache Software License
Requires-Python: >=3.7
License-File: LICENSE
Requires-Dist: asyncpg
Requires-Dist: black
Requires-Dist: boto3
Requires-Dist: cloud-sql-python-connector
Requires-Dist: dacite
Requires-Dist: duckdb
Requires-Dist: clickhouse-connect
Requires-Dist: gcsfs
Requires-Dist: google-api-python-client
Requires-Dist: google-auth
Requires-Dist: google-cloud-bigquery
Requires-Dist: google-cloud-bigquery-storage
Requires-Dist: google-cloud-monitoring
Requires-Dist: google-cloud-pubsub
Requires-Dist: google-cloud-storage
Requires-Dist: grpcio >=1.56.0
Requires-Dist: itsdangerous
Requires-Dist: fastparquet
Requires-Dist: opentelemetry-api
Requires-Dist: opentelemetry-sdk
Requires-Dist: opentelemetry-exporter-otlp
Requires-Dist: opentelemetry-exporter-jaeger
Requires-Dist: pathspec
Requires-Dist: pandas
Requires-Dist: pg8000
Requires-Dist: pulumi ==3.98.0
Requires-Dist: pulumi-aws
Requires-Dist: pulumi-gcp
Requires-Dist: pulumi-snowflake
Requires-Dist: pyarrow
Requires-Dist: pydantic <2.0.2
Requires-Dist: pyyaml !=5.4.0,!=5.4.1,!=6.0.0
Requires-Dist: s3fs
Requires-Dist: sqlalchemy[asyncio]
Requires-Dist: snowflake-ingest
Requires-Dist: ray[default] >=2.4.0
Requires-Dist: ray[serve] >=2.4.0
Requires-Dist: typer[all]
Requires-Dist: redis
Requires-Dist: watchfiles
Provides-Extra: dev
Requires-Dist: aiobotocore ; extra == 'dev'
Requires-Dist: aiohttp ; extra == 'dev'
Requires-Dist: botocore ; extra == 'dev'
Requires-Dist: isort ; extra == 'dev'
Requires-Dist: moto ; extra == 'dev'
Requires-Dist: pytest ; extra == 'dev'
Requires-Dist: pytest-cov ; extra == 'dev'
Requires-Dist: ruff ; extra == 'dev'
Requires-Dist: pre-commit ; extra == 'dev'
Requires-Dist: setuptools ; extra == 'dev'
Requires-Dist: websockets ; extra == 'dev'
Requires-Dist: wheel ; extra == 'dev'
